DEF(POP_TOP, 1)
DEF(ROT_TWO, 2)
DEF(ROT_THREE, 3)
DEF(DUP_TOP, 4)
DEF(DUP_TOP_TWO, 5)
DEF(NOP, 9)
DEF(UNARY_POSITIVE, 10)
DEF(UNARY_NEGATIVE, 11)
DEF(UNARY_NOT, 12)
DEF(UNARY_INVERT, 15)
DEF(BINARY_POWER, 19)
DEF(BINARY_MULTIPLY, 20)
DEF(BINARY_MODULO, 22)
DEF(BINARY_ADD, 23)
DEF(BINARY_SUBTRACT, 24)
DEF(BINARY_SUBSCR, 25)
DEF(BINARY_FLOOR_DIVIDE, 26)
DEF(BINARY_TRUE_DIVIDE, 27)
DEF(INPLACE_FLOOR_DIVIDE, 28)
DEF(INPLACE_TRUE_DIVIDE, 29)
DEF(WITH_EXCEPT_START, 49)
DEF(INPLACE_ADD, 55)
DEF(INPLACE_SUBTRACT, 56)
DEF(INPLACE_MULTIPLY, 57)
DEF(INPLACE_MODULO, 59)
DEF(STORE_SUBSCR, 60)
DEF(DELETE_SUBSCR, 61)
DEF(BINARY_LSHIFT, 62)
DEF(BINARY_RSHIFT, 63)
DEF(BINARY_AND, 64)
DEF(BINARY_XOR, 65)
DEF(BINARY_OR, 66)
DEF(INPLACE_POWER, 67)
DEF(GET_ITER, 68)
DEF(LOAD_BUILD_CLASS, 71)
DEF(INPLACE_LSHIFT, 75)
DEF(INPLACE_RSHIFT, 76)
DEF(INPLACE_AND, 77)
DEF(INPLACE_XOR, 78)
DEF(INPLACE_OR, 79)
DEF(LIST_TO_TUPLE, 82)
DEF(RETURN_VALUE, 83)
DEF(YIELD_VALUE, 86)
DEF(POP_BLOCK, 87)
DEF(POP_EXCEPT, 89)
DEF(STORE_NAME, 90)
DEF(DELETE_NAME, 91)
DEF(UNPACK_SEQUENCE, 92)
DEF(FOR_ITER, 93)
DEF(STORE_ATTR, 95)
DEF(STORE_GLOBAL, 97)
DEF(DELETE_GLOBAL, 98)
DEF(LOAD_CONST, 100)
DEF(LOAD_NAME, 101)
DEF(BUILD_TUPLE, 102)
DEF(BUILD_LIST, 103)
DEF(BUILD_SET, 104)
DEF(BUILD_MAP, 105)
DEF(LOAD_ATTR, 106)
DEF(COMPARE_OP, 107)
DEF(IMPORT_NAME, 108)
DEF(IMPORT_FROM, 109)
DEF(JUMP_FORWARD, 110)
DEF(JUMP_IF_FALSE_OR_POP, 111)
DEF(JUMP_IF_TRUE_OR_POP, 112)
DEF(JUMP_ABSOLUTE, 113)
DEF(POP_JUMP_IF_FALSE, 114)
DEF(POP_JUMP_IF_TRUE, 115)
DEF(LOAD_GLOBAL, 116)
DEF(IS_OP, 117)
DEF(CONTAINS_OP, 118)
DEF(RERAISE, 119)
DEF(JUMP_IF_NOT_EXC_MATCH, 121)
DEF(SETUP_FINALLY, 122)
DEF(LOAD_FAST, 124)
DEF(STORE_FAST, 125)
DEF(DELETE_FAST, 126)
DEF(GEN_START, 129)
DEF(RAISE_VARARGS, 130)
DEF(CALL_FUNCTION, 131)
DEF(MAKE_FUNCTION, 132)
DEF(BUILD_SLICE, 133)
DEF(LOAD_CLOSURE, 135)
DEF(LOAD_DEREF, 136)
DEF(STORE_DEREF, 137)
DEF(CALL_FUNCTION_KW, 141)
DEF(CALL_FUNCTION_EX, 142)
DEF(SETUP_WITH, 143)
DEF(LIST_APPEND, 145)
DEF(SET_ADD, 146)
DEF(LOAD_CLASSDEREF, 148)
DEF(SETUP_ASYNC_WITH, 154)
DEF(FORMAT_VALUE, 155)
DEF(BUILD_CONST_KEY_MAP, 156)
DEF(BUILD_STRING, 157)
DEF(LOAD_METHOD, 160)
DEF(CALL_METHOD, 161)
DEF(LIST_EXTEND, 162)
DEF(SET_UPDATE, 163)
DEF(DICT_MERGE, 164)
DEF(DICT_UPDATE, 165)

DEF(EXCEPT_HANDLER, 257)


