// TODO autogenerate this

#pragma once

#define POP_TOP 1
#define ROT_THREE 3
#define DUP_TOP 4
#define DUP_TOP_TWO 5
#define UNARY_POSITIVE 10
#define UNARY_NEGATIVE 11
#define UNARY_NOT 12
#define UNARY_INVERT 15

#define BINARY_POWER 19
#define BINARY_MULTIPLY 20
#define BINARY_MODULO 22
#define BINARY_ADD 23
#define BINARY_SUBTRACT 24
#define BINARY_SUBSCR 25
#define BINARY_FLOOR_DIVIDE 26
#define BINARY_TRUE_DIVIDE 27
#define INPLACE_FLOOR_DIVIDE 28
#define INPLACE_TRUE_DIVIDE 29
#define INPLACE_ADD 55
#define INPLACE_SUBTRACT 56
#define INPLACE_MULTIPLY 57
#define INPLACE_MODULO 59
#define STORE_SUBSCR 60
#define BINARY_LSHIFT 62
#define BINARY_RSHIFT 63
#define BINARY_AND 64
#define BINARY_XOR 65
#define BINARY_OR 66
#define INPLACE_POWER 67
#define GET_ITER 68
#define LOAD_BUILD_CLASS 71
#define INPLACE_LSHIFT 75
#define INPLACE_RSHIFT 76
#define INPLACE_AND 77
#define INPLACE_XOR 78
#define INPLACE_OR 79
#define LIST_TO_TUPLE 82
#define RETURN_VALUE 83
#define YIELD_VALUE 86
#define HAVE_ARGUMENT 90
#define STORE_NAME 90
#define DELETE_NAME 91
#define UNPACK_SEQUENCE 92
#define FOR_ITER 93
#define STORE_ATTR 95
#define STORE_GLOBAL 97
#define DELETE_GLOBAL 98
#define LOAD_CONST 100
#define LOAD_NAME 101
#define BUILD_TUPLE 102
#define BUILD_LIST 103
#define BUILD_SET 104
#define BUILD_MAP 105
#define LOAD_ATTR 106
#define COMPARE_OP 107
#define JUMP_FORWARD 110
#define JUMP_IF_FALSE_OR_POP 111
#define JUMP_IF_TRUE_OR_POP 112
#define JUMP_ABSOLUTE 113
#define POP_JUMP_IF_FALSE 114
#define POP_JUMP_IF_TRUE 115
#define LOAD_GLOBAL 116
#define IS_OP 117
#define CONTAINS_OP 118
#define RERAISE 119
#define JUMP_IF_NOT_EXC_MATCH 121
#define SETUP_FINALLY 122
#define LOAD_FAST 124
#define STORE_FAST 125
#define DELETE_FAST 126
#define GEN_START 129
#define RAISE_VARARGS 130
#define CALL_FUNCTION 131
#define MAKE_FUNCTION 132
#define BUILD_SLICE 133
#define LOAD_CLOSURE 135
#define LOAD_DEREF 136
#define SETUP_WITH 143
#define LIST_APPEND 145
#define SET_ADD 146
#define LOAD_CLASSDEREF 148
#define SETUP_ASYNC_WITH 154
#define LOAD_METHOD 160
#define CALL_METHOD 161
#define LIST_EXTEND 162
#define SET_UPDATE 163
#define DICT_UPDATE 165

#define HAS_ARG(op) ((op) >= HAVE_ARGUMENT)
